{
  "runs": [
    {
      "model": "mlp",
      "dataset": "bitcoin_alpha",
      "seed": 0,
      "n_params": 123169,
      "elapsed_s": 0.5809741020202637,
      "test_auc": 0.8992881891182158,
      "test_f1_macro": 0.7480902716739775,
      "arch": "mlp_blind"
    },
    {
      "model": "gcn",
      "dataset": "bitcoin_alpha",
      "seed": 0,
      "n_layers": 2,
      "n_params": 125281,
      "elapsed_s": 0.7955694198608398,
      "test_auc": 0.882109313210861,
      "test_f1_macro": 0.7231943018956584,
      "arch": "gcn_blind"
    },
    {
      "model": "signedkan",
      "dataset": "bitcoin_alpha",
      "hidden": 32,
      "seed": 0,
      "lr": 0.05,
      "n_epochs": 200,
      "grid": 5,
      "early_stopping": false,
      "class_weighted": false,
      "spline_kind": "catmull_rom",
      "n_layers": 1,
      "spline_kinds": [
        "catmull_rom"
      ],
      "minibatch": false,
      "batch_size": null,
      "steps_per_epoch": null,
      "triad_loss_alpha": 0.0,
      "triad_loss_margin": 0.5,
      "bce_weight": 1.0,
      "best_epoch": 200,
      "best_val_auc": NaN,
      "n_params": 121729,
      "elapsed_s": 5.283296585083008,
      "entropy_lam0": 0.0,
      "last_h_norm": NaN,
      "last_lam_eff": NaN,
      "test_auc": 0.7243386407198606,
      "test_f1_binary": 0.9693278224929301,
      "test_f1_macro": 0.6945404544563416,
      "arch": "signedkan_L1"
    },
    {
      "model": "hsikan_mixed",
      "dataset": "bitcoin_alpha",
      "hidden": 16,
      "n_layers": 2,
      "grid": 3,
      "seed": 0,
      "n_epochs": 200,
      "lr": 0.05,
      "weight_decay": 0.0,
      "grad_clip": 0.0,
      "coef_smooth_lam": 0.0,
      "participation_lam": 0.0,
      "arities": [
        3,
        4
      ],
      "max_k4": 30000,
      "n_params": 61059,
      "elapsed_s": 13.996232509613037,
      "best_epoch": -1,
      "best_val_auc": -1.0,
      "test_auc": 0.8253741299385574,
      "test_f1_macro": 0.7624662336323332,
      "alpha": [
        0.47312131524086,
        0.5268786549568176
      ],
      "n_tuples_per_arity": {
        "3": 22153,
        "4": 30000
      },
      "arch": "hsikan_mixed_leanest"
    },
    {
      "model": "sgcn",
      "dataset": "bitcoin_alpha",
      "hidden": 32,
      "n_layers": 2,
      "seed": 0,
      "n_epochs": 200,
      "lr": 0.005,
      "weight_decay": 0.0,
      "balance_alpha": 0.5,
      "balance_margin": 1.0,
      "adj_protocol": "full_graph",
      "n_params": 135585,
      "elapsed_s": 1.860124111175537,
      "best_epoch": -1,
      "best_val_auc": -1.0,
      "test_auc": 0.9290680034112884,
      "test_f1_macro": 0.7766958145391977,
      "arch": "sgcn_balance"
    },
    {
      "model": "sigat_attn",
      "dataset": "bitcoin_alpha",
      "seed": 0,
      "hidden": 32,
      "n_heads": 4,
      "n_layers": 1,
      "n_params": 134465,
      "elapsed_s": 29.445146322250366,
      "test_auc": 0.9166880106729414,
      "test_f1_macro": 0.7852354139347784,
      "arch": "sigat_attn"
    },
    {
      "model": "mlp",
      "dataset": "bitcoin_alpha",
      "seed": 1,
      "n_params": 123169,
      "elapsed_s": 0.30310654640197754,
      "test_auc": 0.8984304581549091,
      "test_f1_macro": 0.7415082247383038,
      "arch": "mlp_blind"
    },
    {
      "model": "gcn",
      "dataset": "bitcoin_alpha",
      "seed": 1,
      "n_layers": 2,
      "n_params": 125281,
      "elapsed_s": 0.7024991512298584,
      "test_auc": 0.8466645388750484,
      "test_f1_macro": 0.6995192307692307,
      "arch": "gcn_blind"
    },
    {
      "model": "signedkan",
      "dataset": "bitcoin_alpha",
      "hidden": 32,
      "seed": 1,
      "lr": 0.05,
      "n_epochs": 200,
      "grid": 5,
      "early_stopping": false,
      "class_weighted": false,
      "spline_kind": "catmull_rom",
      "n_layers": 1,
      "spline_kinds": [
        "catmull_rom"
      ],
      "minibatch": false,
      "batch_size": null,
      "steps_per_epoch": null,
      "triad_loss_alpha": 0.0,
      "triad_loss_margin": 0.5,
      "bce_weight": 1.0,
      "best_epoch": 200,
      "best_val_auc": NaN,
      "n_params": 121729,
      "elapsed_s": 5.157296657562256,
      "entropy_lam0": 0.0,
      "last_h_norm": NaN,
      "last_lam_eff": NaN,
      "test_auc": 0.765078506644916,
      "test_f1_binary": 0.9675168955744495,
      "test_f1_macro": 0.6892920446251695,
      "arch": "signedkan_L1"
    },
    {
      "model": "hsikan_mixed",
      "dataset": "bitcoin_alpha",
      "hidden": 16,
      "n_layers": 2,
      "grid": 3,
      "seed": 1,
      "n_epochs": 200,
      "lr": 0.05,
      "weight_decay": 0.0,
      "grad_clip": 0.0,
      "coef_smooth_lam": 0.0,
      "participation_lam": 0.0,
      "arities": [
        3,
        4
      ],
      "max_k4": 30000,
      "n_params": 61059,
      "elapsed_s": 13.907843112945557,
      "best_epoch": -1,
      "best_val_auc": -1.0,
      "test_auc": 0.8297367744452226,
      "test_f1_macro": 0.7480013436345314,
      "alpha": [
        0.43977251648902893,
        0.5602275133132935
      ],
      "n_tuples_per_arity": {
        "3": 22153,
        "4": 30000
      },
      "arch": "hsikan_mixed_leanest"
    },
    {
      "model": "sgcn",
      "dataset": "bitcoin_alpha",
      "hidden": 32,
      "n_layers": 2,
      "seed": 1,
      "n_epochs": 200,
      "lr": 0.005,
      "weight_decay": 0.0,
      "balance_alpha": 0.5,
      "balance_margin": 1.0,
      "adj_protocol": "full_graph",
      "n_params": 135585,
      "elapsed_s": 1.6214187145233154,
      "best_epoch": -1,
      "best_val_auc": -1.0,
      "test_auc": 0.9465968632805226,
      "test_f1_macro": 0.7907264881063985,
      "arch": "sgcn_balance"
    },
    {
      "model": "sigat_attn",
      "dataset": "bitcoin_alpha",
      "seed": 1,
      "hidden": 32,
      "n_heads": 4,
      "n_layers": 1,
      "n_params": 134465,
      "elapsed_s": 29.025699615478516,
      "test_auc": 0.8965095351661895,
      "test_f1_macro": 0.7796474358974359,
      "arch": "sigat_attn"
    },
    {
      "model": "mlp",
      "dataset": "bitcoin_alpha",
      "seed": 2,
      "n_params": 123169,
      "elapsed_s": 0.28580451011657715,
      "test_auc": 0.8947436481006372,
      "test_f1_macro": 0.7362697919315472,
      "arch": "mlp_blind"
    },
    {
      "model": "gcn",
      "dataset": "bitcoin_alpha",
      "seed": 2,
      "n_layers": 2,
      "n_params": 125281,
      "elapsed_s": 0.6977400779724121,
      "test_auc": 0.8558899900686916,
      "test_f1_macro": 0.7349215378327929,
      "arch": "gcn_blind"
    },
    {
      "model": "signedkan",
      "dataset": "bitcoin_alpha",
      "hidden": 32,
      "seed": 2,
      "lr": 0.05,
      "n_epochs": 200,
      "grid": 5,
      "early_stopping": false,
      "class_weighted": false,
      "spline_kind": "catmull_rom",
      "n_layers": 1,
      "spline_kinds": [
        "catmull_rom"
      ],
      "minibatch": false,
      "batch_size": null,
      "steps_per_epoch": null,
      "triad_loss_alpha": 0.0,
      "triad_loss_margin": 0.5,
      "bce_weight": 1.0,
      "best_epoch": 200,
      "best_val_auc": NaN,
      "n_params": 121729,
      "elapsed_s": 5.154975414276123,
      "entropy_lam0": 0.0,
      "last_h_norm": NaN,
      "last_lam_eff": NaN,
      "test_auc": 0.7133666618389473,
      "test_f1_binary": 0.962425840474621,
      "test_f1_macro": 0.6853651693722586,
      "arch": "signedkan_L1"
    },
    {
      "model": "hsikan_mixed",
      "dataset": "bitcoin_alpha",
      "hidden": 16,
      "n_layers": 2,
      "grid": 3,
      "seed": 2,
      "n_epochs": 200,
      "lr": 0.05,
      "weight_decay": 0.0,
      "grad_clip": 0.0,
      "coef_smooth_lam": 0.0,
      "participation_lam": 0.0,
      "arities": [
        3,
        4
      ],
      "max_k4": 30000,
      "n_params": 61059,
      "elapsed_s": 13.920091152191162,
      "best_epoch": -1,
      "best_val_auc": -1.0,
      "test_auc": 0.8395007448481338,
      "test_f1_macro": 0.7537492779777992,
      "alpha": [
        0.4556746780872345,
        0.5443253517150879
      ],
      "n_tuples_per_arity": {
        "3": 22153,
        "4": 30000
      },
      "arch": "hsikan_mixed_leanest"
    },
    {
      "model": "sgcn",
      "dataset": "bitcoin_alpha",
      "hidden": 32,
      "n_layers": 2,
      "seed": 2,
      "n_epochs": 200,
      "lr": 0.005,
      "weight_decay": 0.0,
      "balance_alpha": 0.5,
      "balance_margin": 1.0,
      "adj_protocol": "full_graph",
      "n_params": 135585,
      "elapsed_s": 1.6676578521728516,
      "best_epoch": -1,
      "best_val_auc": -1.0,
      "test_auc": 0.9277109368534303,
      "test_f1_macro": 0.7584125151714629,
      "arch": "sgcn_balance"
    },
    {
      "model": "sigat_attn",
      "dataset": "bitcoin_alpha",
      "seed": 2,
      "hidden": 32,
      "n_heads": 4,
      "n_layers": 1,
      "n_params": 134465,
      "elapsed_s": 29.514968395233154,
      "test_auc": 0.9083526442108748,
      "test_f1_macro": 0.7766082099885521,
      "arch": "sigat_attn"
    },
    {
      "model": "mlp",
      "dataset": "bitcoin_alpha",
      "seed": 3,
      "n_params": 123169,
      "elapsed_s": 0.2907569408416748,
      "test_auc": 0.8801911672403748,
      "test_f1_macro": 0.7402650143878214,
      "arch": "mlp_blind"
    },
    {
      "model": "gcn",
      "dataset": "bitcoin_alpha",
      "seed": 3,
      "n_layers": 2,
      "n_params": 125281,
      "elapsed_s": 0.7271337509155273,
      "test_auc": 0.8770514873723231,
      "test_f1_macro": 0.7083394356570982,
      "arch": "gcn_blind"
    },
    {
      "model": "signedkan",
      "dataset": "bitcoin_alpha",
      "hidden": 32,
      "seed": 3,
      "lr": 0.05,
      "n_epochs": 200,
      "grid": 5,
      "early_stopping": false,
      "class_weighted": false,
      "spline_kind": "catmull_rom",
      "n_layers": 1,
      "spline_kinds": [
        "catmull_rom"
      ],
      "minibatch": false,
      "batch_size": null,
      "steps_per_epoch": null,
      "triad_loss_alpha": 0.0,
      "triad_loss_margin": 0.5,
      "bce_weight": 1.0,
      "best_epoch": 200,
      "best_val_auc": NaN,
      "n_params": 121729,
      "elapsed_s": 5.155563116073608,
      "entropy_lam0": 0.0,
      "last_h_norm": NaN,
      "last_lam_eff": NaN,
      "test_auc": 0.7429051115845884,
      "test_f1_binary": 0.9696837513631407,
      "test_f1_macro": 0.7122928560737272,
      "arch": "signedkan_L1"
    },
    {
      "model": "hsikan_mixed",
      "dataset": "bitcoin_alpha",
      "hidden": 16,
      "n_layers": 2,
      "grid": 3,
      "seed": 3,
      "n_epochs": 200,
      "lr": 0.05,
      "weight_decay": 0.0,
      "grad_clip": 0.0,
      "coef_smooth_lam": 0.0,
      "participation_lam": 0.0,
      "arities": [
        3,
        4
      ],
      "max_k4": 30000,
      "n_params": 61059,
      "elapsed_s": 13.91026759147644,
      "best_epoch": -1,
      "best_val_auc": -1.0,
      "test_auc": 0.8269671902750141,
      "test_f1_macro": 0.7428373241493107,
      "alpha": [
        0.4242432415485382,
        0.5757567882537842
      ],
      "n_tuples_per_arity": {
        "3": 22153,
        "4": 30000
      },
      "arch": "hsikan_mixed_leanest"
    },
    {
      "model": "sgcn",
      "dataset": "bitcoin_alpha",
      "hidden": 32,
      "n_layers": 2,
      "seed": 3,
      "n_epochs": 200,
      "lr": 0.005,
      "weight_decay": 0.0,
      "balance_alpha": 0.5,
      "balance_margin": 1.0,
      "adj_protocol": "full_graph",
      "n_params": 135585,
      "elapsed_s": 1.7804605960845947,
      "best_epoch": -1,
      "best_val_auc": -1.0,
      "test_auc": 0.9246223518186502,
      "test_f1_macro": 0.7565518007556254,
      "arch": "sgcn_balance"
    },
    {
      "model": "sigat_attn",
      "dataset": "bitcoin_alpha",
      "seed": 3,
      "hidden": 32,
      "n_heads": 4,
      "n_layers": 1,
      "n_params": 134465,
      "elapsed_s": 29.477529525756836,
      "test_auc": 0.8951014801951077,
      "test_f1_macro": 0.7718559487147256,
      "arch": "sigat_attn"
    },
    {
      "model": "mlp",
      "dataset": "bitcoin_alpha",
      "seed": 4,
      "n_params": 123169,
      "elapsed_s": 0.29639506340026855,
      "test_auc": 0.8869685964537491,
      "test_f1_macro": 0.7395871530393265,
      "arch": "mlp_blind"
    },
    {
      "model": "gcn",
      "dataset": "bitcoin_alpha",
      "seed": 4,
      "n_layers": 2,
      "n_params": 125281,
      "elapsed_s": 0.7070729732513428,
      "test_auc": 0.8931766716513565,
      "test_f1_macro": 0.7552429054674348,
      "arch": "gcn_blind"
    },
    {
      "model": "signedkan",
      "dataset": "bitcoin_alpha",
      "hidden": 32,
      "seed": 4,
      "lr": 0.05,
      "n_epochs": 200,
      "grid": 5,
      "early_stopping": false,
      "class_weighted": false,
      "spline_kind": "catmull_rom",
      "n_layers": 1,
      "spline_kinds": [
        "catmull_rom"
      ],
      "minibatch": false,
      "batch_size": null,
      "steps_per_epoch": null,
      "triad_loss_alpha": 0.0,
      "triad_loss_margin": 0.5,
      "bce_weight": 1.0,
      "best_epoch": 200,
      "best_val_auc": NaN,
      "n_params": 121729,
      "elapsed_s": 5.153690814971924,
      "entropy_lam0": 0.0,
      "last_h_norm": NaN,
      "last_lam_eff": NaN,
      "test_auc": 0.7758085879085665,
      "test_f1_binary": 0.9662576687116564,
      "test_f1_macro": 0.7041433271094514,
      "arch": "signedkan_L1"
    },
    {
      "model": "hsikan_mixed",
      "dataset": "bitcoin_alpha",
      "hidden": 16,
      "n_layers": 2,
      "grid": 3,
      "seed": 4,
      "n_epochs": 200,
      "lr": 0.05,
      "weight_decay": 0.0,
      "grad_clip": 0.0,
      "coef_smooth_lam": 0.0,
      "participation_lam": 0.0,
      "arities": [
        3,
        4
      ],
      "max_k4": 30000,
      "n_params": 61059,
      "elapsed_s": 13.916856050491333,
      "best_epoch": -1,
      "best_val_auc": -1.0,
      "test_auc": 0.8375218970305491,
      "test_f1_macro": 0.743245713688774,
      "alpha": [
        0.4468859136104584,
        0.553114116191864
      ],
      "n_tuples_per_arity": {
        "3": 22153,
        "4": 30000
      },
      "arch": "hsikan_mixed_leanest"
    },
    {
      "model": "sgcn",
      "dataset": "bitcoin_alpha",
      "hidden": 32,
      "n_layers": 2,
      "seed": 4,
      "n_epochs": 200,
      "lr": 0.005,
      "weight_decay": 0.0,
      "balance_alpha": 0.5,
      "balance_margin": 1.0,
      "adj_protocol": "full_graph",
      "n_params": 135585,
      "elapsed_s": 1.6456029415130615,
      "best_epoch": -1,
      "best_val_auc": -1.0,
      "test_auc": 0.9269201737520473,
      "test_f1_macro": 0.8024165808199961,
      "arch": "sgcn_balance"
    },
    {
      "model": "sigat_attn",
      "dataset": "bitcoin_alpha",
      "seed": 4,
      "hidden": 32,
      "n_heads": 4,
      "n_layers": 1,
      "n_params": 134465,
      "elapsed_s": 28.869721174240112,
      "test_auc": 0.8956148971017589,
      "test_f1_macro": 0.794802009376816,
      "arch": "sigat_attn"
    },
    {
      "model": "mlp",
      "dataset": "bitcoin_otc",
      "seed": 0,
      "n_params": 190305,
      "elapsed_s": 0.2869987487792969,
      "test_auc": 0.9230549359305963,
      "test_f1_macro": 0.8241423338566196,
      "arch": "mlp_blind"
    },
    {
      "model": "gcn",
      "dataset": "bitcoin_otc",
      "seed": 0,
      "n_layers": 2,
      "n_params": 192417,
      "elapsed_s": 0.7100822925567627,
      "test_auc": 0.9150895060609755,
      "test_f1_macro": 0.8102251780735978,
      "arch": "gcn_blind"
    },
    {
      "model": "signedkan",
      "dataset": "bitcoin_otc",
      "hidden": 32,
      "seed": 0,
      "lr": 0.05,
      "n_epochs": 200,
      "grid": 5,
      "early_stopping": false,
      "class_weighted": false,
      "spline_kind": "catmull_rom",
      "n_layers": 1,
      "spline_kinds": [
        "catmull_rom"
      ],
      "minibatch": false,
      "batch_size": null,
      "steps_per_epoch": null,
      "triad_loss_alpha": 0.0,
      "triad_loss_margin": 0.5,
      "bce_weight": 1.0,
      "best_epoch": 200,
      "best_val_auc": NaN,
      "n_params": 188865,
      "elapsed_s": 7.704778671264648,
      "entropy_lam0": 0.0,
      "last_h_norm": NaN,
      "last_lam_eff": NaN,
      "test_auc": 0.8223503207588821,
      "test_f1_binary": 0.9543272952469423,
      "test_f1_macro": 0.7540169002709749,
      "arch": "signedkan_L1"
    },
    {
      "model": "hsikan_mixed",
      "dataset": "bitcoin_otc",
      "hidden": 16,
      "n_layers": 2,
      "grid": 3,
      "seed": 0,
      "n_epochs": 200,
      "lr": 0.05,
      "weight_decay": 0.0,
      "grad_clip": 0.0,
      "coef_smooth_lam": 0.0,
      "participation_lam": 0.0,
      "arities": [
        3,
        4
      ],
      "max_k4": 30000,
      "n_params": 94627,
      "elapsed_s": 16.68524193763733,
      "best_epoch": -1,
      "best_val_auc": -1.0,
      "test_auc": 0.8681309493606238,
      "test_f1_macro": 0.7962303064604609,
      "alpha": [
        0.6786128282546997,
        0.3213872015476227
      ],
      "n_tuples_per_arity": {
        "3": 33493,
        "4": 30000
      },
      "arch": "hsikan_mixed_leanest"
    },
    {
      "model": "sgcn",
      "dataset": "bitcoin_otc",
      "hidden": 32,
      "n_layers": 2,
      "seed": 0,
      "n_epochs": 200,
      "lr": 0.005,
      "weight_decay": 0.0,
      "balance_alpha": 0.5,
      "balance_margin": 1.0,
      "adj_protocol": "full_graph",
      "n_params": 202721,
      "elapsed_s": 1.7153866291046143,
      "best_epoch": -1,
      "best_val_auc": -1.0,
      "test_auc": 0.9495039522370748,
      "test_f1_macro": 0.86041356073182,
      "arch": "sgcn_balance"
    },
    {
      "model": "sigat_attn",
      "dataset": "bitcoin_otc",
      "seed": 0,
      "hidden": 32,
      "n_heads": 4,
      "n_layers": 1,
      "n_params": 201601,
      "elapsed_s": 35.58657169342041,
      "test_auc": 0.9351954207427371,
      "test_f1_macro": 0.8583822678705049,
      "arch": "sigat_attn"
    },
    {
      "model": "mlp",
      "dataset": "bitcoin_otc",
      "seed": 1,
      "n_params": 190305,
      "elapsed_s": 0.2838928699493408,
      "test_auc": 0.9076647423087361,
      "test_f1_macro": 0.8178979729187901,
      "arch": "mlp_blind"
    },
    {
      "model": "gcn",
      "dataset": "bitcoin_otc",
      "seed": 1,
      "n_layers": 2,
      "n_params": 192417,
      "elapsed_s": 0.7129144668579102,
      "test_auc": 0.8860095477758861,
      "test_f1_macro": 0.7811180761092367,
      "arch": "gcn_blind"
    },
    {
      "model": "signedkan",
      "dataset": "bitcoin_otc",
      "hidden": 32,
      "seed": 1,
      "lr": 0.05,
      "n_epochs": 200,
      "grid": 5,
      "early_stopping": false,
      "class_weighted": false,
      "spline_kind": "catmull_rom",
      "n_layers": 1,
      "spline_kinds": [
        "catmull_rom"
      ],
      "minibatch": false,
      "batch_size": null,
      "steps_per_epoch": null,
      "triad_loss_alpha": 0.0,
      "triad_loss_margin": 0.5,
      "bce_weight": 1.0,
      "best_epoch": 200,
      "best_val_auc": NaN,
      "n_params": 188865,
      "elapsed_s": 7.70177960395813,
      "entropy_lam0": 0.0,
      "last_h_norm": NaN,
      "last_lam_eff": NaN,
      "test_auc": 0.7862530883125214,
      "test_f1_binary": 0.9559207495008447,
      "test_f1_macro": 0.7423281908423764,
      "arch": "signedkan_L1"
    },
    {
      "model": "hsikan_mixed",
      "dataset": "bitcoin_otc",
      "hidden": 16,
      "n_layers": 2,
      "grid": 3,
      "seed": 1,
      "n_epochs": 200,
      "lr": 0.05,
      "weight_decay": 0.0,
      "grad_clip": 0.0,
      "coef_smooth_lam": 0.0,
      "participation_lam": 0.0,
      "arities": [
        3,
        4
      ],
      "max_k4": 30000,
      "n_params": 94627,
      "elapsed_s": 16.690922260284424,
      "best_epoch": -1,
      "best_val_auc": -1.0,
      "test_auc": 0.8121847806549162,
      "test_f1_macro": 0.7549476046806767,
      "alpha": [
        0.5740489363670349,
        0.4259510934352875
      ],
      "n_tuples_per_arity": {
        "3": 33493,
        "4": 30000
      },
      "arch": "hsikan_mixed_leanest"
    },
    {
      "model": "sgcn",
      "dataset": "bitcoin_otc",
      "hidden": 32,
      "n_layers": 2,
      "seed": 1,
      "n_epochs": 200,
      "lr": 0.005,
      "weight_decay": 0.0,
      "balance_alpha": 0.5,
      "balance_margin": 1.0,
      "adj_protocol": "full_graph",
      "n_params": 202721,
      "elapsed_s": 1.714658498764038,
      "best_epoch": -1,
      "best_val_auc": -1.0,
      "test_auc": 0.9330853872153552,
      "test_f1_macro": 0.8510559102988404,
      "arch": "sgcn_balance"
    },
    {
      "model": "sigat_attn",
      "dataset": "bitcoin_otc",
      "seed": 1,
      "hidden": 32,
      "n_heads": 4,
      "n_layers": 1,
      "n_params": 201601,
      "elapsed_s": 35.962058544158936,
      "test_auc": 0.9331047717732641,
      "test_f1_macro": 0.8473584809351233,
      "arch": "sigat_attn"
    },
    {
      "model": "mlp",
      "dataset": "bitcoin_otc",
      "seed": 2,
      "n_params": 190305,
      "elapsed_s": 0.30371713638305664,
      "test_auc": 0.9041174947384658,
      "test_f1_macro": 0.7957081957930594,
      "arch": "mlp_blind"
    },
    {
      "model": "gcn",
      "dataset": "bitcoin_otc",
      "seed": 2,
      "n_layers": 2,
      "n_params": 192417,
      "elapsed_s": 0.717693567276001,
      "test_auc": 0.8956682791018846,
      "test_f1_macro": 0.7901964205500963,
      "arch": "gcn_blind"
    },
    {
      "model": "signedkan",
      "dataset": "bitcoin_otc",
      "hidden": 32,
      "seed": 2,
      "lr": 0.05,
      "n_epochs": 200,
      "grid": 5,
      "early_stopping": false,
      "class_weighted": false,
      "spline_kind": "catmull_rom",
      "n_layers": 1,
      "spline_kinds": [
        "catmull_rom"
      ],
      "minibatch": false,
      "batch_size": null,
      "steps_per_epoch": null,
      "triad_loss_alpha": 0.0,
      "triad_loss_margin": 0.5,
      "bce_weight": 1.0,
      "best_epoch": 200,
      "best_val_auc": NaN,
      "n_params": 188865,
      "elapsed_s": 7.712389707565308,
      "entropy_lam0": 0.0,
      "last_h_norm": NaN,
      "last_lam_eff": NaN,
      "test_auc": 0.801344032704153,
      "test_f1_binary": 0.961038961038961,
      "test_f1_macro": 0.7587803500846979,
      "arch": "signedkan_L1"
    },
    {
      "model": "hsikan_mixed",
      "dataset": "bitcoin_otc",
      "hidden": 16,
      "n_layers": 2,
      "grid": 3,
      "seed": 2,
      "n_epochs": 200,
      "lr": 0.05,
      "weight_decay": 0.0,
      "grad_clip": 0.0,
      "coef_smooth_lam": 0.0,
      "participation_lam": 0.0,
      "arities": [
        3,
        4
      ],
      "max_k4": 30000,
      "n_params": 94627,
      "elapsed_s": 16.69636583328247,
      "best_epoch": -1,
      "best_val_auc": -1.0,
      "test_auc": 0.8500595939895466,
      "test_f1_macro": 0.7903802743898656,
      "alpha": [
        0.6404728293418884,
        0.3595271408557892
      ],
      "n_tuples_per_arity": {
        "3": 33493,
        "4": 30000
      },
      "arch": "hsikan_mixed_leanest"
    },
    {
      "model": "sgcn",
      "dataset": "bitcoin_otc",
      "hidden": 32,
      "n_layers": 2,
      "seed": 2,
      "n_epochs": 200,
      "lr": 0.005,
      "weight_decay": 0.0,
      "balance_alpha": 0.5,
      "balance_margin": 1.0,
      "adj_protocol": "full_graph",
      "n_params": 202721,
      "elapsed_s": 1.7076971530914307,
      "best_epoch": -1,
      "best_val_auc": -1.0,
      "test_auc": 0.9450477302862347,
      "test_f1_macro": 0.8463367980786765,
      "arch": "sgcn_balance"
    },
    {
      "model": "sigat_attn",
      "dataset": "bitcoin_otc",
      "seed": 2,
      "hidden": 32,
      "n_heads": 4,
      "n_layers": 1,
      "n_params": 201601,
      "elapsed_s": 35.5561146736145,
      "test_auc": 0.9335673935480553,
      "test_f1_macro": 0.8347016521977038,
      "arch": "sigat_attn"
    },
    {
      "model": "mlp",
      "dataset": "bitcoin_otc",
      "seed": 3,
      "n_params": 190305,
      "elapsed_s": 0.28626012802124023,
      "test_auc": 0.896382592999735,
      "test_f1_macro": 0.801921948522672,
      "arch": "mlp_blind"
    },
    {
      "model": "gcn",
      "dataset": "bitcoin_otc",
      "seed": 3,
      "n_layers": 2,
      "n_params": 192417,
      "elapsed_s": 0.7224125862121582,
      "test_auc": 0.9116759410601583,
      "test_f1_macro": 0.8081574570037693,
      "arch": "gcn_blind"
    },
    {
      "model": "signedkan",
      "dataset": "bitcoin_otc",
      "hidden": 32,
      "seed": 3,
      "lr": 0.05,
      "n_epochs": 200,
      "grid": 5,
      "early_stopping": false,
      "class_weighted": false,
      "spline_kind": "catmull_rom",
      "n_layers": 1,
      "spline_kinds": [
        "catmull_rom"
      ],
      "minibatch": false,
      "batch_size": null,
      "steps_per_epoch": null,
      "triad_loss_alpha": 0.0,
      "triad_loss_margin": 0.5,
      "bce_weight": 1.0,
      "best_epoch": 200,
      "best_val_auc": NaN,
      "n_params": 188865,
      "elapsed_s": 7.712827920913696,
      "entropy_lam0": 0.0,
      "last_h_norm": NaN,
      "last_lam_eff": NaN,
      "test_auc": 0.7948080887053541,
      "test_f1_binary": 0.9504920049200491,
      "test_f1_macro": 0.7138823660963882,
      "arch": "signedkan_L1"
    },
    {
      "model": "hsikan_mixed",
      "dataset": "bitcoin_otc",
      "hidden": 16,
      "n_layers": 2,
      "grid": 3,
      "seed": 3,
      "n_epochs": 200,
      "lr": 0.05,
      "weight_decay": 0.0,
      "grad_clip": 0.0,
      "coef_smooth_lam": 0.0,
      "participation_lam": 0.0,
      "arities": [
        3,
        4
      ],
      "max_k4": 30000,
      "n_params": 94627,
      "elapsed_s": 16.68518352508545,
      "best_epoch": -1,
      "best_val_auc": -1.0,
      "test_auc": 0.8396268904064905,
      "test_f1_macro": 0.7381920635684042,
      "alpha": [
        0.615633487701416,
        0.38436654210090637
      ],
      "n_tuples_per_arity": {
        "3": 33493,
        "4": 30000
      },
      "arch": "hsikan_mixed_leanest"
    },
    {
      "model": "sgcn",
      "dataset": "bitcoin_otc",
      "hidden": 32,
      "n_layers": 2,
      "seed": 3,
      "n_epochs": 200,
      "lr": 0.005,
      "weight_decay": 0.0,
      "balance_alpha": 0.5,
      "balance_margin": 1.0,
      "adj_protocol": "full_graph",
      "n_params": 202721,
      "elapsed_s": 1.7104582786560059,
      "best_epoch": -1,
      "best_val_auc": -1.0,
      "test_auc": 0.938139664232849,
      "test_f1_macro": 0.8521136121942574,
      "arch": "sgcn_balance"
    },
    {
      "model": "sigat_attn",
      "dataset": "bitcoin_otc",
      "seed": 3,
      "hidden": 32,
      "n_heads": 4,
      "n_layers": 1,
      "n_params": 201601,
      "elapsed_s": 35.48832964897156,
      "test_auc": 0.921012863465711,
      "test_f1_macro": 0.8389850541822378,
      "arch": "sigat_attn"
    },
    {
      "model": "mlp",
      "dataset": "bitcoin_otc",
      "seed": 4,
      "n_params": 190305,
      "elapsed_s": 0.28194379806518555,
      "test_auc": 0.9074570944904982,
      "test_f1_macro": 0.8153622737409885,
      "arch": "mlp_blind"
    },
    {
      "model": "gcn",
      "dataset": "bitcoin_otc",
      "seed": 4,
      "n_layers": 2,
      "n_params": 192417,
      "elapsed_s": 0.7229812145233154,
      "test_auc": 0.9190229274866263,
      "test_f1_macro": 0.8175899562284861,
      "arch": "gcn_blind"
    },
    {
      "model": "signedkan",
      "dataset": "bitcoin_otc",
      "hidden": 32,
      "seed": 4,
      "lr": 0.05,
      "n_epochs": 200,
      "grid": 5,
      "early_stopping": false,
      "class_weighted": false,
      "spline_kind": "catmull_rom",
      "n_layers": 1,
      "spline_kinds": [
        "catmull_rom"
      ],
      "minibatch": false,
      "batch_size": null,
      "steps_per_epoch": null,
      "triad_loss_alpha": 0.0,
      "triad_loss_margin": 0.5,
      "bce_weight": 1.0,
      "best_epoch": 200,
      "best_val_auc": NaN,
      "n_params": 188865,
      "elapsed_s": 7.6890623569488525,
      "entropy_lam0": 0.0,
      "last_h_norm": NaN,
      "last_lam_eff": NaN,
      "test_auc": 0.8130046478648407,
      "test_f1_binary": 0.9596206791067605,
      "test_f1_macro": 0.7530062158420401,
      "arch": "signedkan_L1"
    },
    {
      "model": "hsikan_mixed",
      "dataset": "bitcoin_otc",
      "hidden": 16,
      "n_layers": 2,
      "grid": 3,
      "seed": 4,
      "n_epochs": 200,
      "lr": 0.05,
      "weight_decay": 0.0,
      "grad_clip": 0.0,
      "coef_smooth_lam": 0.0,
      "participation_lam": 0.0,
      "arities": [
        3,
        4
      ],
      "max_k4": 30000,
      "n_params": 94627,
      "elapsed_s": 16.684369802474976,
      "best_epoch": -1,
      "best_val_auc": -1.0,
      "test_auc": 0.8554372965167,
      "test_f1_macro": 0.7718039996348864,
      "alpha": [
        0.6790613532066345,
        0.3209386169910431
      ],
      "n_tuples_per_arity": {
        "3": 33493,
        "4": 30000
      },
      "arch": "hsikan_mixed_leanest"
    },
    {
      "model": "sgcn",
      "dataset": "bitcoin_otc",
      "hidden": 32,
      "n_layers": 2,
      "seed": 4,
      "n_epochs": 200,
      "lr": 0.005,
      "weight_decay": 0.0,
      "balance_alpha": 0.5,
      "balance_margin": 1.0,
      "adj_protocol": "full_graph",
      "n_params": 202721,
      "elapsed_s": 1.724316120147705,
      "best_epoch": -1,
      "best_val_auc": -1.0,
      "test_auc": 0.9430367411488245,
      "test_f1_macro": 0.8569102245715823,
      "arch": "sgcn_balance"
    },
    {
      "model": "sigat_attn",
      "dataset": "bitcoin_otc",
      "seed": 4,
      "hidden": 32,
      "n_heads": 4,
      "n_layers": 1,
      "n_params": 201601,
      "elapsed_s": 35.60620665550232,
      "test_auc": 0.9352491545118072,
      "test_f1_macro": 0.8371529207264077,
      "arch": "sigat_attn"
    }
  ],
  "summary": {
    "gcn_blind|bitcoin_alpha": {
      "auc_med": 0.8771,
      "f1m_med": 0.7232,
      "elapsed_med_s": 0.71,
      "n_seeds": 5,
      "auc_seeds": [
        0.8821,
        0.8467,
        0.8559,
        0.8771,
        0.8932
      ],
      "f1m_seeds": [
        0.7232,
        0.6995,
        0.7349,
        0.7083,
        0.7552
      ]
    },
    "gcn_blind|bitcoin_otc": {
      "auc_med": 0.9117,
      "f1m_med": 0.8082,
      "elapsed_med_s": 0.72,
      "n_seeds": 5,
      "auc_seeds": [
        0.9151,
        0.886,
        0.8957,
        0.9117,
        0.919
      ],
      "f1m_seeds": [
        0.8102,
        0.7811,
        0.7902,
        0.8082,
        0.8176
      ]
    },
    "hsikan_mixed_leanest|bitcoin_alpha": {
      "auc_med": 0.8297,
      "f1m_med": 0.748,
      "elapsed_med_s": 13.92,
      "n_seeds": 5,
      "auc_seeds": [
        0.8254,
        0.8297,
        0.8395,
        0.827,
        0.8375
      ],
      "f1m_seeds": [
        0.7625,
        0.748,
        0.7537,
        0.7428,
        0.7432
      ]
    },
    "hsikan_mixed_leanest|bitcoin_otc": {
      "auc_med": 0.8501,
      "f1m_med": 0.7718,
      "elapsed_med_s": 16.69,
      "n_seeds": 5,
      "auc_seeds": [
        0.8681,
        0.8122,
        0.8501,
        0.8396,
        0.8554
      ],
      "f1m_seeds": [
        0.7962,
        0.7549,
        0.7904,
        0.7382,
        0.7718
      ]
    },
    "mlp_blind|bitcoin_alpha": {
      "auc_med": 0.8947,
      "f1m_med": 0.7403,
      "elapsed_med_s": 0.3,
      "n_seeds": 5,
      "auc_seeds": [
        0.8993,
        0.8984,
        0.8947,
        0.8802,
        0.887
      ],
      "f1m_seeds": [
        0.7481,
        0.7415,
        0.7363,
        0.7403,
        0.7396
      ]
    },
    "mlp_blind|bitcoin_otc": {
      "auc_med": 0.9075,
      "f1m_med": 0.8154,
      "elapsed_med_s": 0.29,
      "n_seeds": 5,
      "auc_seeds": [
        0.9231,
        0.9077,
        0.9041,
        0.8964,
        0.9075
      ],
      "f1m_seeds": [
        0.8241,
        0.8179,
        0.7957,
        0.8019,
        0.8154
      ]
    },
    "sgcn_balance|bitcoin_alpha": {
      "auc_med": 0.9277,
      "f1m_med": 0.7767,
      "elapsed_med_s": 1.67,
      "n_seeds": 5,
      "auc_seeds": [
        0.9291,
        0.9466,
        0.9277,
        0.9246,
        0.9269
      ],
      "f1m_seeds": [
        0.7767,
        0.7907,
        0.7584,
        0.7566,
        0.8024
      ]
    },
    "sgcn_balance|bitcoin_otc": {
      "auc_med": 0.943,
      "f1m_med": 0.8521,
      "elapsed_med_s": 1.71,
      "n_seeds": 5,
      "auc_seeds": [
        0.9495,
        0.9331,
        0.945,
        0.9381,
        0.943
      ],
      "f1m_seeds": [
        0.8604,
        0.8511,
        0.8463,
        0.8521,
        0.8569
      ]
    },
    "sigat_attn|bitcoin_alpha": {
      "auc_med": 0.8965,
      "f1m_med": 0.7796,
      "elapsed_med_s": 29.45,
      "n_seeds": 5,
      "auc_seeds": [
        0.9167,
        0.8965,
        0.9084,
        0.8951,
        0.8956
      ],
      "f1m_seeds": [
        0.7852,
        0.7796,
        0.7766,
        0.7719,
        0.7948
      ]
    },
    "sigat_attn|bitcoin_otc": {
      "auc_med": 0.9336,
      "f1m_med": 0.839,
      "elapsed_med_s": 35.59,
      "n_seeds": 5,
      "auc_seeds": [
        0.9352,
        0.9331,
        0.9336,
        0.921,
        0.9352
      ],
      "f1m_seeds": [
        0.8584,
        0.8474,
        0.8347,
        0.839,
        0.8372
      ]
    },
    "signedkan_L1|bitcoin_alpha": {
      "auc_med": 0.7429,
      "f1m_med": 0.6945,
      "elapsed_med_s": 5.16,
      "n_seeds": 5,
      "auc_seeds": [
        0.7243,
        0.7651,
        0.7134,
        0.7429,
        0.7758
      ],
      "f1m_seeds": [
        0.6945,
        0.6893,
        0.6854,
        0.7123,
        0.7041
      ]
    },
    "signedkan_L1|bitcoin_otc": {
      "auc_med": 0.8013,
      "f1m_med": 0.753,
      "elapsed_med_s": 7.7,
      "n_seeds": 5,
      "auc_seeds": [
        0.8224,
        0.7863,
        0.8013,
        0.7948,
        0.813
      ],
      "f1m_seeds": [
        0.754,
        0.7423,
        0.7588,
        0.7139,
        0.753
      ]
    }
  },
  "wall_clock_s": 584.4
}